Metadata-Version: 2.1
Name: intelliml
Version: 0.1
Summary: An Automated Machine Learning Tool
Home-page: 
Author: Mujaffar Bhati
Author-email: mujaffarbhati444@gmail.com
License: MIT
Keywords: automl
Classifier: Development Status :: 5 - Production/Stable
Classifier: Intended Audience :: Education
Classifier: Operating System :: OS Independent
Classifier: License :: OSI Approved :: MIT License
Classifier: Programming Language :: Python :: 3
License-File: LICENSE.txt
Requires-Dist: pandas
Requires-Dist: numpy
Requires-Dist: scikit-learn
Requires-Dist: xgboost
Requires-Dist: lightgbm
